hydrah/__init__.py
hydrah-0.1.1.dist-info/WHEEL
hydrah-0.1.1.dist-info/METADATA
hydrah-0.1.1.dist-info/RECORD
