Metadata-Version: 2.1
Name: hydrah
Version: 0.1.1
Summary: 
Author: Marco Maier
Author-email: mm.maiermarco@gmail.com
Requires-Python: >=3.10,<4.0
Classifier: Programming Language :: Python :: 3
Classifier: Programming Language :: Python :: 3.10
Classifier: Programming Language :: Python :: 3.11
